{
  "updated": "2026-06-20",
  "from_account": "sybeorg@gmail.com",
  "gmail_status": "verified_himalaya_account_available_sybeorg",
  "policy": "Do not send outbound email until Stark approves exact recipients and message content.",
  "first_batch": [
    "bunch-heating-cooling",
    "five-seasons-hvac",
    "mp-plumbing"
  ],
  "queue": [
    {
      "id": "bunch-heating-cooling",
      "business": "Bunch Heating and Cooling",
      "priority": "high",
      "recipient_email": "",
      "recipient_status": "needed",
      "subject": "Quick mockup for Bunch Heating and Cooling",
      "mockup_url": "https://sybeorg-mockups.vercel.app/bunch-heating-cooling/",
      "send_status": "ready_pending_recipient_and_stark_approval"
    },
    {
      "id": "five-seasons-hvac",
      "business": "Five Seasons Heating & Cooling",
      "priority": "high",
      "recipient_email": "",
      "recipient_status": "needed",
      "subject": "Sample page for Five Seasons Heating & Cooling",
      "mockup_url": "https://sybeorg-mockups.vercel.app/five-seasons-hvac/",
      "send_status": "ready_pending_recipient_and_stark_approval"
    },
    {
      "id": "mp-plumbing",
      "business": "M&P Plumbing",
      "priority": "high",
      "recipient_email": "mpplumbingservice@gmail.com",
      "recipient_status": "verified_from_master_send_board_official_site_mailto_schema",
      "subject": "quick mockup idea for M&P Plumbing",
      "mockup_url": "https://sybeorg-mockups.vercel.app/mp-plumbing/",
      "send_status": "ready_pending_stark_approval",
      "draft_path": "outreach/drafts/mp-plumbing-email.eml",
      "review_path": "outreach/drafts/mp-plumbing-email-draft.md",
      "last_prepared": "2026-06-20 02:24 CDT"
    },
    {
      "id": "8-finger-hvac",
      "business": "8 Finger HVAC",
      "priority": "medium",
      "recipient_email": "",
      "recipient_status": "needed",
      "subject": "Bobby — quick mockup for 8 Finger HVAC",
      "mockup_url": "https://sybeorg-mockups.vercel.app/8-finger-hvac/",
      "send_status": "queued_after_first_batch"
    },
    {
      "id": "platinum-phc",
      "business": "Platinum Plumbing, Heating & Cooling",
      "priority": "medium",
      "recipient_email": "",
      "recipient_status": "needed",
      "subject": "Quick mockup for Platinum PHC",
      "mockup_url": "https://sybeorg-mockups.vercel.app/platinum-phc/",
      "send_status": "queued_after_first_batch"
    },
    {
      "id": "richardson-plumbing",
      "business": "Richardson Plumbing",
      "priority": "medium",
      "recipient_email": "",
      "recipient_status": "needed",
      "subject": "John — quick mockup for Richardson Plumbing",
      "mockup_url": "https://sybeorg-mockups.vercel.app/richardson-plumbing/",
      "send_status": "queued_after_first_batch"
    }
  ]
}
